AUTHORS.rst
CONTRIBUTING.rst
HISTORY.rst
LICENSE
MANIFEST.in
README.rst
common-requirements.txt
py2-requirements.txt
py3-requirements.txt
setup.cfg
setup.py
docs/Makefile
docs/authors.rst
docs/conf.py
docs/contributing.rst
docs/history.rst
docs/index.rst
docs/installation.rst
docs/make.bat
docs/readme.rst
docs/troubleshooting.rst
docs/usage.rst
tests/__init__.py
tests/test_then.py
then/__init__.py
then/exceptions.py
then/management.py
then/types.py
then.egg-info/PKG-INFO
then.egg-info/SOURCES.txt
then.egg-info/dependency_links.txt
then.egg-info/entry_points.txt
then.egg-info/not-zip-safe
then.egg-info/pbr.json
then.egg-info/requires.txt
then.egg-info/top_level.txt