Metadata-Version: 1.1
Name: then
Version: 0.1.0
Summary: When "something" THEN send email/sms/telegram/event/execute... or Whatever 
Home-page: https://github.com/Nekmo/then
Author: Nekmo
Author-email: contacto@nekmo.com
License: MIT license
Keywords: then
Platform: UNKNOWN
Classifier: Development Status :: 2 - Pre-Alpha
Classifier: Intended Audience :: Developers
Classifier: License :: OSI Approved :: MIT License
Classifier: Natural Language :: English
Classifier: Programming Language :: Python :: 2
Classifier: Programming Language :: Python :: 2.7
Classifier: Programming Language :: Python :: 3
Classifier: Programming Language :: Python :: 3.4
Classifier: Programming Language :: Python :: 3.5
Classifier: Programming Language :: Python :: 3.6
